bonn_mensa/__init__.py
bonn_mensa/mensa.py
bonn_mensa/version.py
bonn_mensa-1.2.0.dist-info/licenses/LICENSE
bonn_mensa-1.2.0.dist-info/METADATA
bonn_mensa-1.2.0.dist-info/WHEEL
bonn_mensa-1.2.0.dist-info/entry_points.txt
bonn_mensa-1.2.0.dist-info/top_level.txt
bonn_mensa-1.2.0.dist-info/RECORD
