Metadata-Version: 2.4
Name: bonn-mensa
Version: 1.2.0
Summary: Meal plans for university canteens in Bonn
Home-page: https://github.com/alexanderwallau/bonn-mensa
Download-URL: https://github.com/alexanderwallau/bonn-mensa
Author: Felix Blanke
Author-email: info@fblanke.de
Maintainer: Alexander Wallau
Maintainer-email: kontakt@alexanderwallau.de
License: MIT
Project-URL: Bug Tracker, https://github.com/alexanderwallau/bonn-mensa/issues
Project-URL: Source Code, https://github.com/alexanderwallau/bonn-mensa
Classifier: License :: OSI Approved :: MIT License
Classifier: Development Status :: 5 - Production/Stable
Classifier: Environment :: Console
Classifier: Operating System :: OS Independent
Classifier: Programming Language :: Python
Classifier: Programming Language :: Python :: 3.10
Classifier: Programming Language :: Python :: 3.11
Classifier: Programming Language :: Python :: 3 :: Only
Requires-Python: >=3.8
License-File: LICENSE
Requires-Dist: colorama
Requires-Dist: holidays
Requires-Dist: requests
Dynamic: download-url
Dynamic: license-file
